README.md
setup.py
python_for_pytest/__init__.py
python_for_pytest/generate_excel_template.py
python_for_pytest/test_api_for_flask.py
python_for_pytest/test_api_for_sanic.py
python_for_pytest.egg-info/PKG-INFO
python_for_pytest.egg-info/SOURCES.txt
python_for_pytest.egg-info/dependency_links.txt
python_for_pytest.egg-info/requires.txt
python_for_pytest.egg-info/top_level.txt