Metadata-Version: 2.1
Name: python-for-pytest
Version: 0.0.3
Summary: It is simple and fast to use unit testing
Home-page: http://github.com
Author: SunXiuWen
Author-email: xiuwensun@163.com
License: UNKNOWN
Platform: UNKNOWN
Classifier: Programming Language :: Python :: 3
Classifier: License :: OSI Approved :: MIT License
Classifier: Operating System :: OS Independent
Classifier: Topic :: Utilities
